cyclonefw/__init__.py
cyclonefw/core/__init__.py
cyclonefw/core/api.py
cyclonefw/core/app.py
cyclonefw/core/default_config.py
cyclonefw/core/utils.py
cyclonefw/model/__init__.py
cyclonefw/model/model.py
cyclonefw/utils/__init__.py
cyclonefw/utils/config.py
cyclonefw/utils/storage.py
cyclonefw-1.0.23.dist-info/METADATA
cyclonefw-1.0.23.dist-info/WHEEL
cyclonefw-1.0.23.dist-info/top_level.txt
cyclonefw-1.0.23.dist-info/zip-safe
cyclonefw-1.0.23.dist-info/RECORD
